chibi_gob_mx/__init__.py
chibi_gob_mx/chibi_gob_mx.py
chibi_gob_mx/cli.py
chibi_gob_mx/profeco.py
chibi_gob_mx/response.py
chibi_gob_mx/serializers.py
chibi_gob_mx/service.py
chibi_gob_mx-0.0.1.dist-info/AUTHORS.rst
chibi_gob_mx-0.0.1.dist-info/LICENSE
chibi_gob_mx-0.0.1.dist-info/METADATA
chibi_gob_mx-0.0.1.dist-info/WHEEL
chibi_gob_mx-0.0.1.dist-info/entry_points.txt
chibi_gob_mx-0.0.1.dist-info/top_level.txt
chibi_gob_mx-0.0.1.dist-info/RECORD
