Metadata-Version: 2.1
Name: chibi-gob-mx
Version: 0.0.1
Summary: python client for use the open api of gobmx
Home-page: https://github.com/dem4ply/chibi_gob_mx
Author: dem4ply
Author-email: dem4ply@gmail.com
License: WTFPL
Keywords: chibi_gob_mx
Platform: UNKNOWN
Classifier: Development Status :: 2 - Pre-Alpha
Classifier: Intended Audience :: Developers
Classifier: License :: Public Domain
Classifier: Natural Language :: English
Classifier: Programming Language :: Python :: 3.7
Classifier: Programming Language :: Python :: 3.8
Requires-Python: >=2.7, !=3.0.*, !=3.1.*, !=3.2.*, !=3.3.*, !=3.4.*
